.gitignore
CHANGES.rst
LICENSE.txt
Makefile
README.rst
TODO.txt
dev.ini
setup.cfg
setup.py
who.ini
Lasco.egg-info/PKG-INFO
Lasco.egg-info/SOURCES.txt
Lasco.egg-info/dependency_links.txt
Lasco.egg-info/entry_points.txt
Lasco.egg-info/not-zip-safe
Lasco.egg-info/requires.txt
Lasco.egg-info/top_level.txt
docs/Makefile
docs/changes.rst
docs/conf.py
docs/development.rst
docs/features.rst
docs/index.rst
docs/installation.rst
docs/userguide.rst
docs/_build/doctrees/changes.doctree
docs/_build/doctrees/development.doctree
docs/_build/doctrees/environment.pickle
docs/_build/doctrees/features.doctree
docs/_build/doctrees/index.doctree
docs/_build/doctrees/installation.doctree
docs/_build/doctrees/userguide.doctree
docs/_build/html/.buildinfo
docs/_build/html/changes.html
docs/_build/html/development.html
docs/_build/html/features.html
docs/_build/html/genindex.html
docs/_build/html/index.html
docs/_build/html/installation.html
docs/_build/html/objects.inv
docs/_build/html/search.html
docs/_build/html/searchindex.js
docs/_build/html/userguide.html
docs/_build/html/_sources/changes.txt
docs/_build/html/_sources/development.txt
docs/_build/html/_sources/features.txt
docs/_build/html/_sources/index.txt
docs/_build/html/_sources/installation.txt
docs/_build/html/_sources/userguide.txt
docs/_build/html/_static/ajax-loader.gif
docs/_build/html/_static/basic.css
docs/_build/html/_static/comment-bright.png
docs/_build/html/_static/comment-close.png
docs/_build/html/_static/comment.png
docs/_build/html/_static/default.css
docs/_build/html/_static/doctools.js
docs/_build/html/_static/down-pressed.png
docs/_build/html/_static/down.png
docs/_build/html/_static/file.png
docs/_build/html/_static/jquery.js
docs/_build/html/_static/minus.png
docs/_build/html/_static/plus.png
docs/_build/html/_static/pygments.css
docs/_build/html/_static/searchtools.js
docs/_build/html/_static/sidebar.js
docs/_build/html/_static/underscore.js
docs/_build/html/_static/up-pressed.png
docs/_build/html/_static/up.png
docs/_build/html/_static/websupport.js
lasco/__init__.py
lasco/api.py
lasco/app.py
lasco/auth.py
lasco/batch.py
lasco/i18n.py
lasco/lascocli.py
lasco/models.py
lasco/utils.py
lasco/whoplugins.py
