Metadata-Version: 1.0
Name: Lasco
Version: 0.1.0
Summary: Lasco is a web picture gallery.
Home-page: http://readthedocs.org/projects/Lasco
Author: Damien Baty
Author-email: damien.baty.remove@gmail.com
License: UNKNOWN
Keywords: web pyramid image picture gallery
Platform: UNKNOWN
Classifier: Development Status :: 4 - Beta
Classifier: Environment :: Web Environment
Classifier: Framework :: Pyramid
Classifier: License :: OSI Approved :: BSD License
Classifier: Programming Language :: Python
Classifier: Programming Language :: Python :: 2.7
Classifier: Topic :: Internet :: WWW/HTTP
Classifier: Topic :: Internet :: WWW/HTTP :: Dynamic Content
Classifier: Topic :: Internet :: WWW/HTTP :: WSGI
Classifier: Topic :: Internet :: WWW/HTTP :: WSGI :: Application
Classifier: Topic :: Multimedia :: Graphics :: Presentation
